{
  "Wallpapers":
  [
    
    {
      "author": "YeyeBBC",
      "url": "https://raw.githubusercontent.com/antoniacrespoa2/meeye-wallpapers/master/Images/com_abandoned_lock.jpg",
      "thumbUrl": "https://raw.githubusercontent.com/antoniacrespoa2/meeye-wallpapers/master/Thumbnails/abandoned_lock.jpg",
      "name": "Abandoned Lock"
    },
    
    {
      "author": "YeyeBBC",
      "url": "https://raw.githubusercontent.com/antoniacrespoa2/meeye-wallpapers/master/Images/com_lane_of_late_autumn.jpg",
      "thumbUrl": "https://raw.githubusercontent.com/antoniacrespoa2/meeye-wallpapers/master/Thumbnails/lane_of_late_autumn.jpg",
      "name": "Lane of Late Autumn"
    },
    
    {
      "author": "YeyeBBC",
      "url": "https://raw.githubusercontent.com/antoniacrespoa2/meeye-wallpapers/master/Images/com_winter.jpg",
      "thumbUrl": "https://raw.githubusercontent.com/antoniacrespoa2/meeye-wallpapers/master/Thumbnails/winter.jpg",
      "name": "Winter"
    },
    
    {
      "author": "Tyler Lastovich on Unsplash",
      "url": "https://images.unsplash.com/photo-1544687216-294c8cf702f2?ixlib=rb-1.2.1&ixid=eyJhcHBfaWQiOjEyMDd9.jpg",
      "thumbUrl": "https://images.unsplash.com/photo-1544687216-294c8cf702f2?ixlib=rb-1.2.1&ixid=eyJhcHBfaWQiOjEyMDd9.jpg",
      "name": "Breakfast"
    },
    
    {
      "author": "Anh Ha on Unsplash",
      "url": "https://images.unsplash.com/photo-1544681655-6e5bff3ec253?ixlib=rb-1.2.1&ixid=eyJhcHBfaWQiOjEyMDd9.jpg",
      "thumbUrl": "https://images.unsplash.com/photo-1544681655-6e5bff3ec253?ixlib=rb-1.2.1&ixid=eyJhcHBfaWQiOjEyMDd9.jpg",
      "name": "Juice Drinks"
    },
    
    {
      "author": "Clay Bank on Unsplash",
      "url": "https://images.unsplash.com/photo-1544373616-31fb1cae7864?ixlib=rb-1.2.1&fm=jpg&crop=entropy&cs=srgb&ixid=eyJhcHBfaWQiOjIxNTV9.jpg",
      "thumbUrl": "https://images.unsplash.com/photo-1544373616-31fb1cae7864?ixlib=rb-1.2.1&ixid=eyJhcHBfaWQiOjEyMDd9&auto=format&fit=crop&w=750&q=80.jpg",
      "name": "By the Window"
    },
    
    {
      "author": "Blake Cheek on Unsplash",
      "url": "https://images.unsplash.com/photo-1544402316-ad9d0b2e7642?ixlib=rb-1.2.1&fm=jpg&crop=entropy&cs=srgb&ixid=eyJhcHBfaWQiOjIxNTV9.jpg",
      "thumbUrl": "https://images.unsplash.com/photo-1544402316-ad9d0b2e7642?ixlib=rb-1.2.1&ixid=eyJhcHBfaWQiOjEyMDd9&auto=format&fit=crop&w=668&q=80.jpg",
      "name": "Fall is Gone"
    },
    
    {
      "author": "PTMP on Unsplash",
      "url": "https://images.unsplash.com/photo-1544541270-e7a70f7b7984?ixlib=rb-1.2.1&fm=jpg&crop=entropy.jpg",
      "thumbUrl": "https://images.unsplash.com/photo-1544541270-e7a70f7b7984?ixlib=rb-1.2.1&ixid=eyJhcHBfaWQiOjEyMDd9&auto=format&fit=crop&w=1267&q=80.jpg",
      "name": "Sandwitches"
    },
    
    {
      "author": "JuniperPhoton on Unsplash",
      "url": "https://images.unsplash.com/photo-1532885118845-ecfdb20258f6?ixlib=rb-1.2.1&fm=jpg&crop=entropy.jpg",
      "thumbUrl": "https://images.unsplash.com/photo-1532885118845-ecfdb20258f6?ixlib=rb-1.2.1&ixid=eyJhcHBfaWQiOjEyMDd9&auto=format&fit=crop&w=1350&q=80.jpg",
      "name": "Mahola and Lulu"
    },
    
    {
      "author": "JuniperPhoton on Unsplash",
      "url": "https://images.unsplash.com/photo-1532885059790-ac667d74c204?ixlib=rb-1.2.1&fm=jpg&crop=entropy.jpg",
      "thumbUrl": "https://images.unsplash.com/photo-1532885059790-ac667d74c204?ixlib=rb-1.2.1&ixid=eyJhcHBfaWQiOjEyMDd9&auto=format&fit=crop&w=594&q=80.jpg",
      "name": "Mahola and Lulu"
    },
    
    {
      "author": "Irina Grigoras on Unsplash",
      "url": "https://images.unsplash.com/photo-1533007414914-8f8f2510939e?ixlib=rb-1.2.1&fm=jpg&crop=entropy.jpg",
      "thumbUrl": "https://images.unsplash.com/photo-1533007414914-8f8f2510939e?ixlib=rb-1.2.1&auto=format&fit=crop&w=668&q=80.jpg",
      "name": "Overnight Oatmeal"
    },
    
    {
      "author": "Dragne Marius on Unsplash",
      "url": "https://images.unsplash.com/photo-1470119693884-47d3a1d1f180?ixlib=rb-1.2.1&fm=jpg&crop=entropy.jpg",
      "thumbUrl": "https://images.unsplash.com/photo-1470119693884-47d3a1d1f180?ixlib=rb-1.2.1&ixid=eyJhcHBfaWQiOjEyMDd9&auto=format&fit=crop&w=788&q=80.jpg",
      "name": "Grilled Corn"
    },
    
    {
      "author": "Neha Deshmukh on Unsplash",
      "url": "https://images.unsplash.com/photo-1424591185129-8a73a1111adf?ixlib=rb-1.2.1&fm=jpg&crop=entropy.jpg",
      "thumbUrl": "https://images.unsplash.com/photo-1424591185129-8a73a1111adf?ixlib=rb-1.2.1&ixid=eyJhcHBfaWQiOjEyMDd9&auto=format&fit=crop&w=668&q=80.jpg",
      "name": "Cookies Cooking"
    },
    
    {
      "author": "Rikki Austin on Unsplash",
      "url": "https://images.unsplash.com/photo-1542041205924-7c13b56e8835?ixlib=rb-1.2.1&fm=jpg&crop=entropy.jpg",
      "thumbUrl": "https://images.unsplash.com/photo-1542041205924-7c13b56e8835?ixlib=rb-1.2.1&ixid=eyJhcHBfaWQiOjEyMDd9&auto=format&fit=crop&w=668&q=80.jpg",
      "name": "Candles"
    },
    
    {
      "author": "Keith Champaco on Unsplash",
      "url": "https://images.unsplash.com/photo-1543792660-470a955d9735?ixlib=rb-1.2.1&fm=jpg&crop=entropy.jpg",
      "thumbUrl": "https://images.unsplash.com/photo-1543792660-470a955d9735?ixlib=rb-1.2.1&ixid=eyJhcHBfaWQiOjEyMDd9&auto=format&fit=crop&w=668&q=80",
      "name": "The Lauae"
    },
    
    {
      "author": "Craig Whitehead on Unsplash",
      "url": "https://images.unsplash.com/photo-1494018405518-a1c52e534bad?ixlib=rb-1.2.1&fm=jpg&crop=entropy.jpg",
      "thumbUrl": "https://images.unsplash.com/photo-1494018405518-a1c52e534bad?ixlib=rb-1.2.1&ixid=eyJhcHBfaWQiOjEyMDd9&auto=format&fit=crop&w=802&q=80",
      "name": "Cambridge"
    },
    
    {
      "author": "freezydreamin on Unsplash",
      "url": "https://images.unsplash.com/flagged/photo-1554443877-b2ea8132bab7?ixlib=rb-1.2.1&fm=jpg&crop=entropy.jpg",
      "thumbUrl": "https://images.unsplash.com/flagged/photo-1554443877-b2ea8132bab7?ixlib=rb-1.2.1&auto=format&fit=crop&w=668&q=80",
      "name": "Nights in Alaska"
    }
    
    
  ]
}
